fiblat/._cube_lattice.py.un~
fiblat/._irrational.py.un~
fiblat/._sphere_lattice.py.un~
fiblat/__init__.py
fiblat/_cube_lattice.py
fiblat/_irrational.py
fiblat/_sphere_lattice.py
fiblat/py.typed
fiblat-0.7.0.dist-info/METADATA
fiblat-0.7.0.dist-info/WHEEL
fiblat-0.7.0.dist-info/licenses/LICENSE
fiblat-0.7.0.dist-info/RECORD
