Metadata-Version: 2.4
Name: fiblat
Version: 0.7.0
Summary: A package for generating evenly distributed points on a sphere
License-Expression: MIT
License-File: LICENSE
Requires-Python: >=3.13
Requires-Dist: numba>=0.61.0
Requires-Dist: numpy>=2.1.3
